{"cameraMode":{"drawMode":0,"name":"Shaded","section":"Shading Mode"},"sceneLighting":false,"audioPlay":false,"sceneViewState":{"showFog":true,"showMaterialUpdate":false,"showSkybox":false,"showFlares":true,"showImageEffects":true,"showParticleSystems":true},"in2DMode":false,"pivot":{"x":-3.182718276977539,"y":-1.5288748741149903,"z":11.609394073486329},"rotation":{"x":-0.19045133888721467,"y":-0.06121283397078514,"z":0.011899538338184357,"w":-0.9797141551971436},"size":4.619761943817139,"orthographic":false}